suspy/__init__.py
suspy/babio3.py
suspy/basis.py
suspy/bethe_green_function.py
suspy/dmft.py
suspy/fft.py
suspy/fit.py
suspy/holstein.py
suspy/impurity_green_function.py
suspy/input_data.txt
suspy/xi_tools.py
suspy-1.0.11.data/scripts/scr
suspy-1.0.11.dist-info/METADATA
suspy-1.0.11.dist-info/WHEEL
suspy-1.0.11.dist-info/top_level.txt
suspy-1.0.11.dist-info/RECORD
