Metadata-Version: 2.1
Name: suspy
Version: 1.0.11
Summary: Package for calculating susceptibility
Home-page: https://github.com/AlexLoner/holstein
Author: Alex_Loner and NVD
Author-email: UNKNOWN
License: UNKNOWN
Platform: UNKNOWN
